{"[\ucde8\uc5c5\uc815\ubcf4]\u00a0[\ud55c\uad6d\ud574\uc591\uad50\ud1b5\uc548\uc804\uacf5\ub2e8]\uac80\uc0ac\uc9c1, \uc6b4\ud56d\uad00\ub9ac\uc9c1, \uc5f0\uad6c\uc9c1, \uc77c\ubc18 \ub4f1 ...": {"date": "2023-07-17", "href": "https://www.jnu.ac.kr//WebApp/web/HOM/COM/Board/board.aspx?boardID=5&bbsMode=view&page=2&key=56962"}, "[\ud559\uc0ac\uc548\ub0b4]\u00a0\uc81c2\uae30 2030\uc790\ubb38\ub2e8(\uccad\ub144\uc815\ucc45\uc704\uc6d0\ub2e8) \ubaa8\uc9d1": {"date": "2023-07-17", "href": "https://www.jnu.ac.kr//WebApp/web/HOM/COM/Board/board.aspx?boardID=5&bbsMode=view&page=2&key=56961"}, "[\ubaa8\uc9d1\uacf5\uace0]\u00a0[2023 GLOBAL TALENT FAIR] \ud574\uc678\ucde8\uc5c5, \uc678\uad6d...": {"date": "2023-07-17", "href": "https://www.jnu.ac.kr//WebApp/web/HOM/COM/Board/board.aspx?boardID=5&bbsMode=view&page=2&key=56960"}, "[\ucde8\uc5c5\uc815\ubcf4]\u00a0[\uc720\ub124\uc2a4\ucf54 \uc544\ud0dc\uad50\uc721\uc6d0] \uad6d\uc81c\uc774\uc0ac\ud68c \ub4f1 \uae30\ud68d\ud589\uc815\uc5c5\ubb34(\uc721\uc544\ud734\uc9c1\ub300\uccb4...": {"date": "2023-07-17", "href": "https://www.jnu.ac.kr//WebApp/web/HOM/COM/Board/board.aspx?boardID=5&bbsMode=view&page=2&key=56959"}, "[\ucde8\uc5c5\uc815\ubcf4]\u00a0[\ud480\ubb34\uc6d0] \uc601\uc5c5 \ubc0f \ub9c8\ucf00\ud305 \ucc44\uc6a9(~7.27.(\ubaa9)\uae4c\uc9c0)": {"date": "2023-07-17", "href": "https://www.jnu.ac.kr//WebApp/web/HOM/COM/Board/board.aspx?boardID=5&bbsMode=view&page=2&key=56958"}, "[\ucde8\uc5c5\uc815\ubcf4]\u00a0[\ubc14\ucee4\ucf00\ubbf8\uce7c\ucf54\ub9ac\uc544] HR/GA \ub2f4\ub2f9\uc790 \ucc44\uc6a9(~\ucc44\uc6a9\uc2dc\uae4c\uc9c0)": {"date": "2023-07-17", "href": "https://www.jnu.ac.kr//WebApp/web/HOM/COM/Board/board.aspx?boardID=5&bbsMode=view&page=2&key=56957"}, "[\ucde8\uc5c5\uc815\ubcf4]\u00a0[\uc18c\ud504\ud2b8\uc6e8\uc5b4\uc815\ucc45\uc5f0\uad6c\uc18c]\uc18c\ud504\ud2b8\uc6e8\uc5b4 \uc815\ucc45\uc5f0\uad6c\uc6d0 \ucc44\uc6a9(~7.31.(...": {"date": "2023-07-17", "href": "https://www.jnu.ac.kr//WebApp/web/HOM/COM/Board/board.aspx?boardID=5&bbsMode=view&page=2&key=56956"}, "[\ucde8\uc5c5\uc815\ubcf4]\u00a0[\ud604\ub300\uc624\ud1a0\uc5d0\ubc84]23\ub144 3\ubd84\uae30 \ucc28\ub7c9\uc804\uc7a5SW, \ucc28\ub7c9\uc751\uc6a9SW, IC...": {"date": "2023-07-17", "href": "https://www.jnu.ac.kr//WebApp/web/HOM/COM/Board/board.aspx?boardID=5&bbsMode=view&page=2&key=56955"}, "[\ucde8\uc5c5\uc815\ubcf4]\u00a0[(\uc8fc)\ucc9c\ubcf4(\ucf54\uc2a4\ub2e5 \uc2dc\ucd1d 8\uc704)] \uc2e0\uc785\uc0ac\uc6d0 QA, QC, \ud658\uacbd...": {"date": "2023-07-17", "href": "https://www.jnu.ac.kr//WebApp/web/HOM/COM/Board/board.aspx?boardID=5&bbsMode=view&page=2&key=56954"}, "[\ucc44\uc6a9\uacf5\uace0]\u00a0\uc804\ub0a8\ub300\ud559\uad50 \uc0dd\uccb4\uc7ac\ub8cc\uac1c\ubc1c\uc13c\ud130 \uc9c1\uc6d0(\uc0ac\uc5c5 \uc6b4\uc601) \ucc44\uc6a9 \uc7ac\uacf5\uace0": {"date": "2023-07-17", "href": "https://www.jnu.ac.kr//WebApp/web/HOM/COM/Board/board.aspx?boardID=5&bbsMode=view&page=2&key=56953"}}